[
  {
    "listing": "/tutorials/index.html",
    "items": []
  },
  {
    "listing": "/mrisoftware/index.html",
    "items": [
      "/mrisoftware/3D-Slicer.html"
    ]
  },
  {
    "listing": "/mrimethods/index.html",
    "items": [
      "/mrimethods/eeg-fmri/gradient-removal.html",
      "/mrimethods/eeg-fmri/ballistocardiogram-removal.html"
    ]
  },
  {
    "listing": "/scienceresources/index.html",
    "items": []
  },
  {
    "listing": "/studentresources/index.html",
    "items": []
  },
  {
    "listing": "/investigatorresources/index.html",
    "items": []
  },
  {
    "listing": "/orientation/index.html",
    "items": [
      "/orientation/mrisafetyfaq.html",
      "/orientation/instantmessaging.html"
    ]
  },
  {
    "listing": "/mriscanners/index.html",
    "items": []
  }
]